naas_abi_marketplace/__demo__/agents/MultiModelAgent.py
naas_abi_marketplace/__demo__/agents/MultiModelAgent_test.py
naas_abi_marketplace/__demo__/apps/dashboard.py
naas_abi_marketplace/__demo__/apps/calendar/scheduling_interface.py
naas_abi_marketplace/__demo__/apps/dashboard/financial_dashboard.py
naas_abi_marketplace/__demo__/apps/reconciliation/account_reconciliation.py
naas_abi_marketplace/__demo__/apps/streamlit/__init__.py
naas_abi_marketplace/__demo__/orchestration/__init__.py
naas_abi_marketplace/__demo__/orchestration/definitions.py
naas_abi_marketplace/__demo__/workflows/ExecutePythonCodeWorkflow.py
naas_abi_marketplace/__demo__/workflows/ExecutePythonCodeWorkflow_test.py
naas_abi_marketplace/ai/chatgpt/__init__.py
naas_abi_marketplace/ai/chatgpt/conftest.py
naas_abi_marketplace/ai/chatgpt/agents/ChatGPTAgent.py
naas_abi_marketplace/ai/chatgpt/agents/ChatGPTAgent_test.py
naas_abi_marketplace/ai/chatgpt/agents/ChatGPTResearchAgent.py
naas_abi_marketplace/ai/chatgpt/agents/ChatGPTResearchAgent_test.py
naas_abi_marketplace/ai/chatgpt/integrations/OpenAIIntegration.py
naas_abi_marketplace/ai/chatgpt/integrations/OpenAIIntegration_test.py
naas_abi_marketplace/ai/chatgpt/integrations/OpenAIResponsesIntegration.py
naas_abi_marketplace/ai/chatgpt/integrations/OpenAIResponsesIntegration_test.py
naas_abi_marketplace/ai/chatgpt/models/gpt_4_1.py
naas_abi_marketplace/ai/chatgpt/models/gpt_4_1_mini.py
naas_abi_marketplace/ai/chatgpt/models/gpt_4o.py
naas_abi_marketplace/ai/chatgpt/models/gpt_5.py
naas_abi_marketplace/ai/chatgpt/models/gpt_5_mini.py
naas_abi_marketplace/ai/chatgpt/models/gpt_5_nano.py
naas_abi_marketplace/ai/chatgpt/models/o3_deep_research.py
naas_abi_marketplace/ai/chatgpt/models/o3_mini.py
naas_abi_marketplace/ai/chatgpt/models/o4_mini_deep_research.py
naas_abi_marketplace/ai/claude/__init__.py
naas_abi_marketplace/ai/claude/agents/ClaudeAgent.py
naas_abi_marketplace/ai/claude/agents/ClaudeAgent_test.py
naas_abi_marketplace-1.4.0.dist-info/METADATA
naas_abi_marketplace-1.4.0.dist-info/WHEEL
naas_abi_marketplace-1.4.0.dist-info/top_level.txt
naas_abi_marketplace-1.4.0.dist-info/RECORD
