Metadata-Version: 2.4
Name: naas-abi-marketplace
Version: 1.4.0
Summary: Add your description here
Author-email: Maxime Jublou <maxime@naas.ai>, Florent Ravenel <florent@naas.ai>, Jeremy Ravenel <jeremy@naas.ai>
License: MIT License
Project-URL: Homepage, https://github.com/jupyter-naas/abi
Project-URL: Repository, https://github.com/jupyter-naas/abi/tree/main/libs/naas-abi-marketplace
Requires-Python: <4,>=3.10
Requires-Dist: naas-abi-core>=1.4.0
Provides-Extra: ai-chatgpt
Requires-Dist: pdfplumber>=0.11.8; extra == "ai-chatgpt"
Provides-Extra: ai-claude
Requires-Dist: langchain-anthropic>=0.3.17; extra == "ai-claude"
Provides-Extra: ai-deepseek
Requires-Dist: langchain-ollama>=0.3.4; extra == "ai-deepseek"
Provides-Extra: ai-gemini
Requires-Dist: langchain-google-genai>=2.1.4; extra == "ai-gemini"
Provides-Extra: ai-gemma
Requires-Dist: langchain-ollama>=0.3.4; extra == "ai-gemma"
Provides-Extra: ai-grok
Requires-Dist: langchain-xai>=0.2.5; extra == "ai-grok"
Provides-Extra: ai-llama
Requires-Dist: langchain-ollama>=0.3.4; extra == "ai-llama"
Provides-Extra: ai-mistral
Requires-Dist: langchain-mistralai>=0.2.11; extra == "ai-mistral"
Provides-Extra: ai-perplexity
Requires-Dist: langchain-perplexity>=0.1.2; extra == "ai-perplexity"
Provides-Extra: ai-qwen
Requires-Dist: langchain-ollama>=0.3.4; extra == "ai-qwen"
Provides-Extra: applications-agicap
Provides-Extra: applications-airtable
Provides-Extra: applications-algolia
Requires-Dist: algoliasearch>=4.35.0; extra == "applications-algolia"
Provides-Extra: applications-arxiv
Requires-Dist: arxiv<3,>=2.1.3; extra == "applications-arxiv"
Provides-Extra: applications-bodo
Requires-Dist: boto3<2,>=1.38.19; extra == "applications-bodo"
Provides-Extra: applications-datagouv
Provides-Extra: applications-exchangeratesapi
Provides-Extra: applications-git
Provides-Extra: applications-github
Requires-Dist: pynacl<2,>=1.5.0; extra == "applications-github"
Provides-Extra: applications-gmail
Provides-Extra: applications-google-calendar
Provides-Extra: applications-google-drive
Provides-Extra: applications-google-sheets
Provides-Extra: applications-googlesearch
Requires-Dist: beautifulsoup4>=4.12.0; extra == "applications-googlesearch"
Provides-Extra: applications-hubspot
Provides-Extra: applications-linkedin
Requires-Dist: pandas>=2.3.3; extra == "applications-linkedin"
Provides-Extra: applications-naas
Provides-Extra: applications-nebari
Provides-Extra: applications-newsapi
Provides-Extra: applications-notion
Provides-Extra: applications-openrouter
Provides-Extra: applications-openweathermap
Provides-Extra: applications-pennylane
Provides-Extra: applications-postgres
Requires-Dist: psycopg2-binary<3,>=2.9.10; extra == "applications-postgres"
Requires-Dist: types-psycopg2>=2.9.21.20251012; extra == "applications-postgres"
Provides-Extra: applications-powerpoint
Requires-Dist: python-pptx<2,>=1.0.2; extra == "applications-powerpoint"
Provides-Extra: applications-pubmed
Requires-Dist: ratelimit>=2.2.1; extra == "applications-pubmed"
Requires-Dist: dagster>=1.11.12; extra == "applications-pubmed"
Requires-Dist: dagster-webserver>=1.11.12; extra == "applications-pubmed"
Requires-Dist: dagster-postgres>=0.27.12; extra == "applications-pubmed"
Requires-Dist: dagster-aws>=0.27.12; extra == "applications-pubmed"
Provides-Extra: applications-sanax
Provides-Extra: applications-sendgrid
Provides-Extra: applications-sharepoint
Provides-Extra: applications-spotify
Provides-Extra: applications-worldbank
Provides-Extra: applications-yahoofinance
Requires-Dist: yfinance==0.2.66; extra == "applications-yahoofinance"
Requires-Dist: yahooquery==2.4.1; extra == "applications-yahoofinance"
